dat1/__init__.py
dat1/app.py
dat1_cli-0.3.0.dist-info/METADATA
dat1_cli-0.3.0.dist-info/WHEEL
dat1_cli-0.3.0.dist-info/entry_points.txt
dat1_cli-0.3.0.dist-info/top_level.txt
dat1_cli-0.3.0.dist-info/RECORD
