Metadata-Version: 2.4
Name: dat1-cli
Version: 0.3.0
License: MIT
Requires-Dist: typer>=0.9.0
Requires-Dist: inquirer>=3.1.3
Requires-Dist: boto3>=1.35.43
Requires-Dist: pyyaml>=6.0.2
Requires-Dist: yaspin>=3.1.0
Requires-Dist: docker>=7.1.0
Requires-Dist: globre>=0.1.5
